KratosMultiphysics/ConstitutiveLawsApplication/__init__.py
KratosMultiphysics/ConstitutiveLawsApplication/__init__.pyi
KratosMultiphysics/ConstitutiveLawsApplication/apply_pre_stressing_imposed_strain_process.py
KratosMultiphysics/ConstitutiveLawsApplication/element_deactivation_process.py
KratosMultiphysics/ConstitutiveLawsApplication/high_cycle_fatigue_analysis.py
KratosMultiphysics/ConstitutiveLawsApplication/set_automated_initial_damage_process.py
KratosMultiphysics/ConstitutiveLawsApplication/set_up_pre_stressed_oriented_composite_materials.py
KratosMultiphysics/ConstitutiveLawsApplication/symbolic_generation/hyper_elastic_simo_taylor_neo_hookean/generate_hyper_elastic_simo_taylor_neo_hookean.py
KratosMultiphysics/ConstitutiveLawsApplication/symbolic_generation/iso_damage_tangent_tensor/isotropic_damage_automatic_differentiation.py
KratosMultiphysics/.libs/KratosConstitutiveLawsApplication.cpython-312-x86_64-linux-gnu.so
KratosMultiphysics/.libs/libKratosConstitutiveLawsCore.so
kratosconstitutivelawsapplication-10.4.0.dist-info/METADATA
kratosconstitutivelawsapplication-10.4.0.dist-info/WHEEL
kratosconstitutivelawsapplication-10.4.0.dist-info/RECORD
